cynergy/__init__.py
cynergy/attributes.py
cynergy/config.py
cynergy/container.py
cynergy/errors/ContainerException.py
cynergy/errors/__init__.py
errors/ContainerException.py
errors/__init__.py
cynergy-1.2.0.dist-info/LICENSE.txt
cynergy-1.2.0.dist-info/METADATA
cynergy-1.2.0.dist-info/WHEEL
cynergy-1.2.0.dist-info/top_level.txt
cynergy-1.2.0.dist-info/RECORD
