Metadata-Version: 2.1
Name: cynergy
Version: 1.2.0
Summary: Dependency injection and inversion of control and library for simple service handling
Home-page: https://github.com/omersaraf/IOCynergy
Author: omersaraf
Author-email: omersaraf.develop@gmail.com
License: UNKNOWN
Project-URL: Bug Reports, https://github.com/omersaraf/IOCynergy/issues
Project-URL: Source, https://github.com/omersaraf/IOCynergy
Keywords: ioc di dependency injection inversion of control service singleton
Platform: UNKNOWN
Classifier: Development Status :: 3 - Alpha
Classifier: Intended Audience :: Developers
Classifier: Topic :: Software Development :: Libraries
Classifier: License :: OSI Approved :: MIT License
Classifier: Programming Language :: Python :: 3
Classifier: Programming Language :: Python :: 3.4
Classifier: Programming Language :: Python :: 3.5
Classifier: Programming Language :: Python :: 3.6
Classifier: Programming Language :: Python :: 3.7
Requires-Python: >=3
Provides-Extra: dev
Provides-Extra: test
